mdl_toolkit/__init__.py
mdl_toolkit/cli.py
mdl_toolkit/conversation.py
mdl_toolkit/convert_dataset.py
mdl_toolkit/inference.py
mdl_toolkit/train.py
mdl_toolkit-0.1.0.dist-info/METADATA
mdl_toolkit-0.1.0.dist-info/WHEEL
mdl_toolkit-0.1.0.dist-info/entry_points.txt
mdl_toolkit-0.1.0.dist-info/top_level.txt
mdl_toolkit-0.1.0.dist-info/RECORD
