Metadata-Version: 2.4
Name: mdl-toolkit
Version: 0.1.0
Summary: A user-friendly MiDashengLM fine-tuning toolkit.
License-Expression: Apache-2.0
Project-URL: Homepage, https://github.com/xiaomi-research/dasheng-lm
Project-URL: Repository, https://github.com/xiaomi-research/dasheng-lm
Project-URL: Issues, https://github.com/xiaomi-research/dasheng-lm/issues
Keywords: MiDashengLM,fine-tuning
Classifier: Programming Language :: Python :: 3
Classifier: Programming Language :: Python :: 3 :: Only
Classifier: Programming Language :: Python :: 3.10
Classifier: Programming Language :: Python :: 3.11
Classifier: Programming Language :: Python :: 3.12
Classifier: Programming Language :: Python :: 3.13
Classifier: Topic :: Scientific/Engineering :: Artificial Intelligence
Requires-Python: >=3.10
Requires-Dist: datasets[audio]>=3.6.0
Requires-Dist: peft>=0.16.0
Requires-Dist: pydantic>=2.11.7
Requires-Dist: pydantic-settings[yaml]>=2.10.1
Requires-Dist: transformers[torch,torch-speech]>=4.56.2
Requires-Dist: typing-extensions>=4.14.1
Provides-Extra: modelscope
Requires-Dist: modelscope>=1.29.1; extra == "modelscope"
Provides-Extra: quantization
Requires-Dist: bitsandbytes>=0.47.0; extra == "quantization"
